{"features":[{"geometry":{"coordinates":[-71.12013459205627,42.40740894206996,17],"type":"Point"},"properties":{"description":"","id":"marker-holzhucp","marker-color":"#1087bf","marker-size":"medium","marker-symbol":"","title":"Ballou Hall"},"type":"Feature"},{"geometry":{"coordinates":[-71.12207651138306,42.40824865050679,17],"type":"Point"},"properties":{"description":"","id":"marker-holzj5nt","marker-color":"#1087bf","marker-size":"medium","marker-symbol":"","title":"Houston Hall"},"type":"Feature"}],"id":"josulliv101.gdn4o3le","type":"FeatureCollection"}